LICENSE.txt
MANIFEST.in
README.rst
setup.cfg
setup.py
bdusers/__init__.py
bdusers/bdusers.py
bdusers.egg-info/PKG-INFO
bdusers.egg-info/SOURCES.txt
bdusers.egg-info/dependency_links.txt
bdusers.egg-info/top_level.txt
test/__init__.py
test/test_simple.py