Metadata-Version: 1.0
Name: bdusers
Version: 3.0
Summary: A bdusers Python project
Home-page: https://github.com/jaritgor
Author: Users
Author-email: joseantoniorita@campusciff.net
License: MIT
Keywords: testing,logging,example
Platform: UNKNOWN
